recursor_mcp/__init__.py
recursor_mcp/__main__.py
recursor_mcp/client.py
recursor_mcp/http_bridge.py
recursor_mcp/resources.py
recursor_mcp/server.py
recursor_mcp/tools.py
recursor_mcp-1.0.1.dist-info/METADATA
recursor_mcp-1.0.1.dist-info/WHEEL
recursor_mcp-1.0.1.dist-info/entry_points.txt
recursor_mcp-1.0.1.dist-info/licenses/LICENSE
recursor_mcp-1.0.1.dist-info/RECORD
