Metadata-Version: 2.4
Name: recursor-mcp
Version: 1.0.1
Summary: Recursor MCP Server - AI model context protocol integration
Author-email: Recursor <team@recursor.dev>
License-Expression: MIT
License-File: LICENSE
Keywords: ai,context,llm,mcp,memory,recursor
Classifier: Development Status :: 4 - Beta
Classifier: Intended Audience :: Developers
Classifier: License :: OSI Approved :: MIT License
Classifier: Operating System :: OS Independent
Classifier: Programming Language :: Python :: 3
Classifier: Programming Language :: Python :: 3.10
Classifier: Programming Language :: Python :: 3.11
Classifier: Programming Language :: Python :: 3.12
Requires-Python: >=3.10
Requires-Dist: aiohttp>=3.9.0
Requires-Dist: mcp>=0.1.0
Requires-Dist: python-dotenv>=1.0.0
